pywmi/__init__.py
pywmi/__main__.py
pywmi/convert.py
pywmi/domain.py
pywmi/engine.py
pywmi/errors.py
pywmi/export.py
pywmi/install.py
pywmi/normalize_weight.py
pywmi/parse.py
pywmi/plot.py
pywmi/sample.py
pywmi/smt_check.py
pywmi/smt_math.py
pywmi/smt_print.py
pywmi/smt_walk.py
pywmi/temp.py
pywmi/engines/__init__.py
pywmi/engines/adaptive_rejection.py
pywmi/engines/algebraic_backend.py
pywmi/engines/convex_integrator.py
pywmi/engines/latte_backend.py
pywmi/engines/pa.py
pywmi/engines/praise.py
pywmi/engines/rejection.py
pywmi/engines/xadd.py
pywmi/engines/pyxadd/__init__.py
pywmi/engines/pyxadd/algebra.py
pywmi/engines/pyxadd/core.py
pywmi/engines/pyxadd/decision.py
pywmi/engines/pyxadd/engine.py
pywmi/engines/pyxadd/leaf_transform.py
pywmi/engines/pyxadd/operation.py
pywmi/engines/pyxadd/reduce.py
pywmi/engines/pyxadd/resolve.py
pywmi/engines/pyxadd/view.py
pywmi/engines/pyxadd/walk.py
pywmi/engines/xsdd/__init__.py
pywmi/engines/xsdd/draw.py
pywmi/engines/xsdd/engine.py
pywmi/engines/xsdd/evaluator.py
pywmi/engines/xsdd/hal_xsdd.py
pywmi/engines/xsdd/inference.py
pywmi/engines/xsdd/piecewise.py
pywmi/engines/xsdd/sdd_iterator.py
pywmi/engines/xsdd/semiring.py
pywmi/engines/xsdd/smt2pl.py
pywmi/engines/xsdd/smt_to_sdd.py
pywmi/engines/xsdd/vtree.py
pywmi/parser/__init__.py
pywmi/parser/minizinc/__init__.py
pywmi/parser/minizinc/minizincErrorListener.py
pywmi/parser/minizinc/minizincParser.py
pywmi/parser/minizinc/visitor.py
pywmi/parser/minizinc/antlr/__init__.py
pywmi/parser/minizinc/antlr/minizincLexer.py
pywmi/parser/minizinc/antlr/minizincListener.py
pywmi/parser/minizinc/antlr/minizincParser.py
pywmi/parser/minizinc/antlr/minizincVisitor.py
pywmi/parser/smtlib/__init__.py
pywmi/parser/smtlib/smtlibErrorListener.py
pywmi/parser/smtlib/smtlibParser.py
pywmi/parser/smtlib/visitor.py
pywmi/parser/smtlib/antlr/SMTLIBv2Lexer.py
pywmi/parser/smtlib/antlr/__init__.py
pywmi/parser/smtlib/antlr/smtlibLexer.py
pywmi/parser/smtlib/antlr/smtlibListener.py
pywmi-0.7.15.dist-info/METADATA
pywmi-0.7.15.dist-info/WHEEL
pywmi-0.7.15.dist-info/entry_points.txt
pywmi-0.7.15.dist-info/top_level.txt
pywmi-0.7.15.dist-info/RECORD
