Metadata-Version: 2.1
Name: pywmi
Version: 0.7.15
Summary: Essential tools and interfaces for WMI solving.
Home-page: http://github.com/samuelkolb/pywmi
Author: Samuel Kolb
Author-email: samuel.kolb@me.com
License: MIT
Platform: UNKNOWN
Classifier: License :: OSI Approved :: MIT License
Classifier: Programming Language :: Python
Classifier: Programming Language :: Python :: 3
Requires-Python: >=3.5.0
Requires-Dist: pysmt
Requires-Dist: numpy
Requires-Dist: future
Requires-Dist: matplotlib
Requires-Dist: pillow
Requires-Dist: polytope
Requires-Dist: tabulate
Requires-Dist: graphviz
Requires-Dist: sympy
Requires-Dist: scipy (>=1.2)
Requires-Dist: autodora (>=0.3.3)
Requires-Dist: deprecated
Requires-Dist: networkx
Requires-Dist: antlr4-python3-runtime
Provides-Extra: sdd
Requires-Dist: pysdd ; extra == 'sdd'
